README.md
setup.py
bread/tools/data/__init__.py
bread/tools/data/array_builder.py
bread/tools/data/batch_random.py
bread/tools/data/feature_encode.py
bread/tools/data/storage.py
bread/tools/file/__init__.py
bread/tools/file/configurator.py
bread/tools/file/path.py
bread/tools/log/__init__.py
bread/tools/log/logger.py
bread/tools/net/__init__.py
bread/tools/net/ws_server.py
bread/tools/text/__init__.py
bread/tools/text/segment.py
bread/tools/text/similar.py
bread/tools/text/string.py
bread_tools.egg-info/PKG-INFO
bread_tools.egg-info/SOURCES.txt
bread_tools.egg-info/dependency_links.txt
bread_tools.egg-info/top_level.txt